bpl_next/__init__.py
bpl_next/_util.py
bpl_next/base.py
bpl_next/dixon_coles.py
bpl_next/dynamic_dixon_coles.py
bpl_next/extended_dixon_coles.py
bpl_next/neutral_dixon_coles.py
bpl_next/neutral_dixon_coles_WC.py
bpl_next-0.4.0.dist-info/METADATA
bpl_next-0.4.0.dist-info/WHEEL
bpl_next-0.4.0.dist-info/licenses/LICENSE
bpl_next-0.4.0.dist-info/RECORD
