Metadata-Version: 2.4
Name: bpl-next
Version: 0.4.0
Summary: Bayesian models for football match prediction, based on Dixon and Coles (1997).
Author-email: Angus Williams <anguswilliams91@gmail.com>
License-Expression: MIT
License-File: LICENSE
Requires-Python: >=3.9
Requires-Dist: black>=24.2.0
Requires-Dist: isort>=5.13.2
Requires-Dist: numpyro>=0.13.2
Requires-Dist: pylint>=3.0.4
Requires-Dist: pytest-cov>=4.1.0
Requires-Dist: pytest>=8.0.1
Requires-Dist: scipy>=1.12.0
